caterpillar/__init__.py
caterpillar/__main__.py
caterpillar/caterpillar.py
caterpillar/download.py
caterpillar/events.py
caterpillar/merge.py
caterpillar/persistence.py
caterpillar/utils.py
caterpillar/variants.py
caterpillar/version.py
caterpillar_hls-1.1.dist-info/COPYING
caterpillar_hls-1.1.dist-info/METADATA
caterpillar_hls-1.1.dist-info/WHEEL
caterpillar_hls-1.1.dist-info/entry_points.txt
caterpillar_hls-1.1.dist-info/top_level.txt
caterpillar_hls-1.1.dist-info/RECORD
