Metadata-Version: 2.1
Name: caterpillar-hls
Version: 1.1
Summary: Hardened HLS merger
Home-page: https://github.com/zmwangx/caterpillar
Author: Zhiming Wang
Author-email: zmwangx@gmail.com
License: MIT
Keywords: HLS streaming m3u8 concatenate merge
Platform: UNKNOWN
Classifier: Development Status :: 5 - Production/Stable
Classifier: Intended Audience :: Developers
Classifier: Intended Audience :: End Users/Desktop
Classifier: License :: OSI Approved :: MIT License
Classifier: Programming Language :: Python :: 3
Classifier: Programming Language :: Python :: 3.6
Classifier: Programming Language :: Python :: 3.7
Classifier: Programming Language :: Python :: 3 :: Only
Classifier: Topic :: Multimedia :: Video
Classifier: Topic :: Multimedia :: Video :: Conversion
Requires-Python: >=3.6
Requires-Dist: xdgappdirs (>=1.4.4.3)
Requires-Dist: click
Requires-Dist: m3u8
Requires-Dist: peewee
Requires-Dist: requests
Provides-Extra: dev
Requires-Dist: black ; extra == 'dev'
Requires-Dist: flake8 ; extra == 'dev'
Requires-Dist: mypy ; extra == 'dev'
Requires-Dist: pylint ; extra == 'dev'
Requires-Dist: pytest ; extra == 'dev'
